AUTHORS
CHANGES.md
LICENSE
MANIFEST.in
README.rst
requirements.txt
run_tests.py
setup.py
doc/README.md
doc/build.sh
doc/refs.bib
doc/tutorial.md
examples/randplot.py
examples/timing_benchmarks.py
polytope/__init__.py
polytope/commit_hash.txt
polytope/esp.py
polytope/plot.py
polytope/polytope.py
polytope/prop2partition.py
polytope/quickhull.py
polytope/solvers.py
polytope/version.py
polytope.egg-info/PKG-INFO
polytope.egg-info/SOURCES.txt
polytope.egg-info/dependency_links.txt
polytope.egg-info/requires.txt
polytope.egg-info/top_level.txt
requirements/README.md
requirements/default.txt
requirements/extras.txt
requirements/test.txt
tests/demo.py
tests/mldivide_test.py
tests/plot_test.py
tests/polytope_test.py