Metadata-Version: 2.1
Name: polytope
Version: 0.2.5
Summary: Polytope Toolbox
Home-page: https://tulip-control.org
Author: Caltech Control and Dynamical Systems
Author-email: polytope@tulip-control.org
License: BSD
Project-URL: Bug Tracker, https://github.com/tulip-control/polytope/issues
Project-URL: Documentation, https://tulip-control.github.io/polytope/
Project-URL: Source Code, https://github.com/tulip-control/polytope
Classifier: Development Status :: 2 - Pre-Alpha
Classifier: Intended Audience :: Developers
Classifier: Intended Audience :: Science/Research
Classifier: License :: OSI Approved :: BSD License
Classifier: Operating System :: OS Independent
Classifier: Programming Language :: Python
Classifier: Programming Language :: Python :: 3
Classifier: Programming Language :: Python :: 3.8
Classifier: Programming Language :: Python :: 3.9
Classifier: Programming Language :: Python :: 3.10
Classifier: Programming Language :: Python :: 3.11
Classifier: Topic :: Scientific/Engineering
Classifier: Topic :: Software Development
Requires-Python: >=3.8
License-File: LICENSE
License-File: AUTHORS
Requires-Dist: networkx>=3.0
Requires-Dist: numpy>=1.24.1
Requires-Dist: scipy>=1.10.0
